poneglyph/__init__.py
poneglyph/agents/__init__.py
poneglyph/agents/poneglyph.py
poneglyph-0.0.2.dist-info/LICENSE
poneglyph-0.0.2.dist-info/METADATA
poneglyph-0.0.2.dist-info/WHEEL
poneglyph-0.0.2.dist-info/RECORD
