Metadata-Version: 2.1
Name: poneglyph
Version: 0.0.2
Summary: 
License: MIT
Author: VISHNU V S
Author-email: vishnuvskvkl@gmail.com
Requires-Python: >=3.8,<4.0
Classifier: License :: OSI Approved :: MIT License
Classifier: Programming Language :: Python :: 3
Classifier: Programming Language :: Python :: 3.8
Classifier: Programming Language :: Python :: 3.9
Classifier: Programming Language :: Python :: 3.10
Classifier: Programming Language :: Python :: 3.11
Classifier: Programming Language :: Python :: 3.12
Requires-Dist: openai (>=1.42.0,<2.0.0)
